{"is_source_file": false, "format": "", "description": "", "external_files": [], "external_methods": [], "published": [], "classes": [], "methods": [], "calls": [], "search-terms": [], "state": 2, "file_id": 11, "knowledge_revision": 54, "git_revision": "37c6d9e053e7a6880ba360b8e6db7da9bc5dfa9d", "hash": "756d60240b95f9752adb98920764a8ca", "format-version": 4, "code-base-name": "tic_tac_toe_frontend", "filename": "tic_tac_toe_frontend/src/app/app.component.html", "revision_history": [{"54": "37c6d9e053e7a6880ba360b8e6db7da9bc5dfa9d"}]}